{
	"name": "RunJob",
	"properties": {
		"annotations": [],
		"runtimeState": "Stopped",
		"pipelines": [
			{
				"pipelineReference": {
					"referenceName": "pl_first",
					"type": "PipelineReference"
				}
			}
		],
		"type": "BlobEventsTrigger",
		"typeProperties": {
			"blobPathBeginsWith": "/population/blobs/population_by_age.tsv.gz",
			"ignoreEmptyBlobs": true,
			"scope": "/subscriptions/4d0e9b79-51f6-4dba-a862-c4549da42f4f/resourceGroups/DataFactory/providers/Microsoft.Storage/storageAccounts/adfprem",
			"events": [
				"Microsoft.Storage.BlobCreated"
			]
		}
	}
}